pylibfreenect2/__init__.py
pylibfreenect2/libfreenect2.cpython-35m-darwin.so
pylibfreenect2-0.1.1.dist-info/DESCRIPTION.rst
pylibfreenect2-0.1.1.dist-info/METADATA
pylibfreenect2-0.1.1.dist-info/RECORD
pylibfreenect2-0.1.1.dist-info/WHEEL
pylibfreenect2-0.1.1.dist-info/metadata.json
pylibfreenect2-0.1.1.dist-info/top_level.txt
tests/__init__.py
tests/test_libfreenect2.py
