Metadata-Version: 2.0
Name: pylibfreenect2
Version: 0.1.1
Summary: A python interface for libfreenect2
Home-page: https://github.com/r9y9/pylibfreenect2
Author: Ryuichi Yamamoto
Author-email: zryuichi@gmail.com
License: MIT
Keywords: pylibfreenect2,libfreenect2,freenect2
Platform: UNKNOWN
Classifier: Operating System :: POSIX
Classifier: Operating System :: Unix
Classifier: Operating System :: MacOS
Classifier: Programming Language :: Cython
Classifier: Programming Language :: Python
Classifier: Programming Language :: Python :: 2
Classifier: Programming Language :: Python :: 2.7
Classifier: Programming Language :: Python :: 3
Classifier: Programming Language :: Python :: 3.4
Classifier: Programming Language :: Python :: 3.5
Classifier: License :: OSI Approved :: MIT License
Classifier: Topic :: Scientific/Engineering
Classifier: Topic :: Software Development
Classifier: Intended Audience :: Science/Research
Classifier: Intended Audience :: Developers
Requires-Dist: numpy (>=1.7.0)
Provides-Extra: develop
Requires-Dist: cython (>=0.21.0); extra == 'develop'
Provides-Extra: docs
Requires-Dist: numpydoc; extra == 'docs'
Requires-Dist: seaborn; extra == 'docs'
Requires-Dist: sphinx-rtd-theme; extra == 'docs'
Provides-Extra: test
Requires-Dist: nose; extra == 'test'
